cloudsmith_cli/__init__.py
cloudsmith_cli/__main__.py
cloudsmith_cli/cli/__init__.py
cloudsmith_cli/cli/command.py
cloudsmith_cli/cli/config.py
cloudsmith_cli/cli/decorators.py
cloudsmith_cli/cli/exceptions.py
cloudsmith_cli/cli/table.py
cloudsmith_cli/cli/types.py
cloudsmith_cli/cli/utils.py
cloudsmith_cli/cli/validators.py
cloudsmith_cli/cli/commands/__init__.py
cloudsmith_cli/cli/commands/check.py
cloudsmith_cli/cli/commands/copy.py
cloudsmith_cli/cli/commands/delete.py
cloudsmith_cli/cli/commands/docs.py
cloudsmith_cli/cli/commands/entitlements.py
cloudsmith_cli/cli/commands/help_.py
cloudsmith_cli/cli/commands/list_.py
cloudsmith_cli/cli/commands/login.py
cloudsmith_cli/cli/commands/main.py
cloudsmith_cli/cli/commands/move.py
cloudsmith_cli/cli/commands/push.py
cloudsmith_cli/cli/commands/repos.py
cloudsmith_cli/cli/commands/resync.py
cloudsmith_cli/cli/commands/status.py
cloudsmith_cli/cli/commands/tags.py
cloudsmith_cli/cli/commands/whoami.py
cloudsmith_cli/cli/commands/metrics/__init__.py
cloudsmith_cli/cli/commands/metrics/command.py
cloudsmith_cli/cli/commands/metrics/entitlements.py
cloudsmith_cli/cli/commands/metrics/packages.py
cloudsmith_cli/cli/commands/quota/__init__.py
cloudsmith_cli/cli/commands/quota/command.py
cloudsmith_cli/cli/commands/quota/history.py
cloudsmith_cli/cli/commands/quota/quota.py
cloudsmith_cli/core/__init__.py
cloudsmith_cli/core/pagination.py
cloudsmith_cli/core/ratelimits.py
cloudsmith_cli/core/rest.py
cloudsmith_cli/core/utils.py
cloudsmith_cli/core/version.py
cloudsmith_cli/core/api/__init__.py
cloudsmith_cli/core/api/distros.py
cloudsmith_cli/core/api/entitlements.py
cloudsmith_cli/core/api/exceptions.py
cloudsmith_cli/core/api/files.py
cloudsmith_cli/core/api/init.py
cloudsmith_cli/core/api/metrics.py
cloudsmith_cli/core/api/packages.py
cloudsmith_cli/core/api/quota.py
cloudsmith_cli/core/api/rates.py
cloudsmith_cli/core/api/repos.py
cloudsmith_cli/core/api/status.py
cloudsmith_cli/core/api/user.py
cloudsmith_cli_testfork-0.29.0.dist-info/LICENSE
cloudsmith_cli_testfork-0.29.0.dist-info/METADATA
cloudsmith_cli_testfork-0.29.0.dist-info/WHEEL
cloudsmith_cli_testfork-0.29.0.dist-info/entry_points.txt
cloudsmith_cli_testfork-0.29.0.dist-info/top_level.txt
cloudsmith_cli_testfork-0.29.0.dist-info/RECORD
